analytics/__init__.py
analytics/admin.py
analytics/adminUtils.py
analytics/apps.py
analytics/config.py
analytics/models.py
analytics/tests.py
analytics/urls.py
analytics/version.py
analytics/views.py
analytics/jinja_renderer/__init__.py
analytics/jinja_renderer/jinja_filters.py
analytics/jinja_renderer/jinja_globals.py
analytics/jinja_renderer/jinja_renderer.py
analytics/management/__init__.py
analytics/management/commands/__init__.py
analytics/management/commands/data_processing.py
analytics/migrations/0001_initial.py
analytics/migrations/0002_query.py
analytics/migrations/0003_alter_apicall_options_alter_figure_options_and_more.py
analytics/migrations/0004_alter_query_database_alter_query_query.py
analytics/migrations/0005_alter_figure_type.py
analytics/migrations/0006_dashboard_backgroundcolor.py
analytics/migrations/0007_alter_dashboard_backgroundcolor.py
analytics/migrations/0008_alter_dashboard_backgroundcolor.py
analytics/migrations/0009_jinjarender.py
analytics/migrations/__init__.py
analytics/static/css/analytics/analytics.css
analytics/static/js/analytics/analytics.js
analytics/static/js/libs/chart.min.js
analytics/static/js/libs/chroma.min.js
analytics/static/js/libs/jquery.min.js
analytics/static/js/libs/touch.js
analytics/templates/analytics.html
analytics/templates/dashboard_change_template.html
analytics/templates/jinja_render.html
th_django_analytics-1.1.1.dist-info/LICENSE
th_django_analytics-1.1.1.dist-info/METADATA
th_django_analytics-1.1.1.dist-info/WHEEL
th_django_analytics-1.1.1.dist-info/top_level.txt
th_django_analytics-1.1.1.dist-info/RECORD
